sparse_lmm/LMM.py
sparse_lmm/VariableSelection_new.py
sparse_lmm/__init__.py
sparse_lmm/helpingMethods.py
sparse_lmm-1.4.dist-info/LICENSE.txt
sparse_lmm-1.4.dist-info/METADATA
sparse_lmm-1.4.dist-info/WHEEL
sparse_lmm-1.4.dist-info/top_level.txt
sparse_lmm-1.4.dist-info/RECORD
